cort_si/CoRT_builder.py
cort_si/SI_CoRT.py
cort_si/over_conditioning.py
cort_si/parametric.py
cort_si/solve_interval.py
cort_si/utils.py
cort_si-0.0.2.dist-info/METADATA
cort_si-0.0.2.dist-info/WHEEL
cort_si-0.0.2.dist-info/top_level.txt
cort_si-0.0.2.dist-info/RECORD
