Metadata-Version: 2.4
Name: cort-si
Version: 0.0.2
Summary: Selective inference framework for Co-Regularization Transfer (CoRT)
License: MIT
Project-URL: Homepage, https://github.com/Park-Hip/Selective_Inference_For_CoRT/tree/main
Classifier: Programming Language :: Python :: 3
Classifier: Operating System :: OS Independent
Requires-Python: >=3.7
Requires-Dist: matplotlib>=3.10.8
Requires-Dist: mpmath>=1.3.0
Requires-Dist: numpy>=2.3.5
Requires-Dist: pandas>=2.3.3
Requires-Dist: scikit-learn>=1.8.0
Requires-Dist: scipy>=1.16.3
Requires-Dist: seaborn>=0.13.2
Requires-Dist: stats>=0.1.2a0
